MANIFEST.in
README.md
setup.cfg
setup.py
sleety/__init__.py
sleety/connection.py
sleety/error.py
sleety/region.py
sleety.egg-info/PKG-INFO
sleety.egg-info/SOURCES.txt
sleety.egg-info/dependency_links.txt
sleety.egg-info/requires.txt
sleety.egg-info/top_level.txt
sleety/auth/__init__.py
sleety/auth/sigv2.py
sleety/computing/__init__.py
sleety/computing/connection.py
sleety/computing/disk.py
sleety/computing/error.py
sleety/computing/fw.py
sleety/computing/instance.py
sleety/computing/lb.py
sleety/computing/region.py
sleety/computing/schema/AttachVolumeResponse.xsd
sleety/computing/schema/CreateVolumeResponse.xsd
sleety/computing/schema/DescribeInstancesResponse.xsd
sleety/computing/schema/DescribeLoadBalancersResponse.xsd
sleety/computing/schema/DescribeRegionsResponse.xsd
sleety/computing/schema/DescribeSecurityGroupsResponse.xsd
sleety/computing/schema/DescribeVolumesResponse.xsd
sleety/computing/schema/DetachVolumeResponse.xsd
sleety/computing/schema/Response.xsd
sleety/computing/schema/_OnlyReturnResponse.xsd
sleety/utils/__init__.py
sleety/utils/response.py
test/unit/__init__.py
test/unit/auth/__init__.py
test/unit/auth/test_sigv2.py
test/unit/computing/__init__.py
test/unit/computing/test_connection.py