Metadata-Version: 1.0
Name: sleety
Version: 0.3.0
Summary: SDK for NIFCLOUD
Home-page: https://github.com/heriet/sleety
Author: heriet
Author-email: heriet@heriet.info
License: MIT
Platform: UNKNOWN
